{
  "navigationDrawer": {
    "color": {
      "background": {
        "value": "$theme.color.common.background",
        "type": "color"
      }
    },
    "spacing": {
      "desktop": {
        "horizontal": {
          "value": "$basic.size.scale.desktop.200",
          "type": "spacing"
        },
        "vertical": {
          "value": "$basic.size.scale.desktop.100",
          "type": "spacing"
        }
      },
      "mobile": {
        "horizontal": {
          "value": "$basic.size.scale.mobile.none",
          "type": "spacing"
        },
        "vertical": {
          "value": "$basic.size.scale.mobile.100",
          "type": "spacing"
        }
      }
    },
    "size": {
      "desktop": {
        "width": {
          "expanded": {
            "value": "248",
            "type": "sizing"
          },
          "collapsed": {
            "value": "74",
            "type": "sizing"
          }
        }
      }
    }
  }
}